{"pageProps":{"comments":[{"id":"15","hotelId":"15","createdAt":"2020-04-10T11:17:11.705Z","idUsers":66,"comment":"Solutions incentivize knowledge user","author":"Miss Matt Abbott","hotel":{"id":"15","createdAt":"2020-04-10T14:02:22.309Z","name":"Megane Gislason","image":"http://lorempixel.com/640/480/people","description":"Expanded granular","price":"473.00","lng":"-15.6004","lat":"116.4424","like":33019,"streetAdress":"692 Dessie Rapid","status":false,"star":3,"countryAdress":"Libyan Arab Jamahiriya","stateAdress":"Hawaii"}},{"id":"58","hotelId":"15","createdAt":"2020-04-10T09:24:34.281Z","idUsers":5,"comment":"Quality-focused Frozen","author":"Mr. Jade Hintz","hotel":{"id":"15","createdAt":"2020-04-10T14:02:22.309Z","name":"Megane Gislason","image":"http://lorempixel.com/640/480/people","description":"Expanded granular","price":"473.00","lng":"-15.6004","lat":"116.4424","like":33019,"streetAdress":"692 Dessie Rapid","status":false,"star":3,"countryAdress":"Libyan Arab Jamahiriya","stateAdress":"Hawaii"}}],"hotel":{"id":"15","createdAt":"2020-04-10T14:02:22.309Z","name":"Megane Gislason","image":"http://lorempixel.com/640/480/people","description":"Expanded granular","price":"473.00","lng":"-15.6004","lat":"116.4424","like":33019,"streetAdress":"692 Dessie Rapid","status":false,"star":3,"countryAdress":"Libyan Arab Jamahiriya","stateAdress":"Hawaii"}},"__N_SSG":true}