{"pageProps":{"comments":[{"id":"25","hotelId":"25","createdAt":"2020-04-10T06:25:30.109Z","idUsers":51,"comment":"users","author":"Jamison Konopelski","hotel":{"id":"25","createdAt":"2020-04-10T05:16:49.044Z","name":"Miracle Hoeger","image":"http://lorempixel.com/640/480/business","description":"Strategist","price":"771.00","lng":"28.5288","lat":"122.9883","like":68626,"streetAdress":"3291 Keanu Squares","status":false,"star":12,"countryAdress":"Yemen","stateAdress":"Louisiana"}},{"id":"68","hotelId":"25","createdAt":"2020-04-10T23:57:13.519Z","idUsers":78,"comment":"Sausages","author":"Conor Balistreri","hotel":{"id":"25","createdAt":"2020-04-10T05:16:49.044Z","name":"Miracle Hoeger","image":"http://lorempixel.com/640/480/business","description":"Strategist","price":"771.00","lng":"28.5288","lat":"122.9883","like":68626,"streetAdress":"3291 Keanu Squares","status":false,"star":12,"countryAdress":"Yemen","stateAdress":"Louisiana"}}],"hotel":{"id":"25","createdAt":"2020-04-10T05:16:49.044Z","name":"Miracle Hoeger","image":"http://lorempixel.com/640/480/business","description":"Strategist","price":"771.00","lng":"28.5288","lat":"122.9883","like":68626,"streetAdress":"3291 Keanu Squares","status":false,"star":12,"countryAdress":"Yemen","stateAdress":"Louisiana"}},"__N_SSG":true}