{"pageProps":{"comments":[{"id":"36","hotelId":"36","createdAt":"2020-04-10T10:16:59.622Z","idUsers":91,"comment":"card","author":"Kavon Wintheiser","hotel":{"id":"36","createdAt":"2020-04-10T11:36:51.736Z","name":"Mrs. Morris Parisian","image":"http://lorempixel.com/640/480/people","description":"bandwidth backing up harness","price":"780.00","lng":"-30.3584","lat":"-164.7018","like":53176,"streetAdress":"9304 Kameron Coves","status":true,"star":100,"countryAdress":"French Guiana","stateAdress":"New Jersey"}},{"id":"79","hotelId":"36","createdAt":"2020-04-11T03:41:19.008Z","idUsers":50,"comment":"open-source input","author":"Veda Tremblay","hotel":{"id":"36","createdAt":"2020-04-10T11:36:51.736Z","name":"Mrs. Morris Parisian","image":"http://lorempixel.com/640/480/people","description":"bandwidth backing up harness","price":"780.00","lng":"-30.3584","lat":"-164.7018","like":53176,"streetAdress":"9304 Kameron Coves","status":true,"star":100,"countryAdress":"French Guiana","stateAdress":"New Jersey"}}],"hotel":{"id":"36","createdAt":"2020-04-10T11:36:51.736Z","name":"Mrs. Morris Parisian","image":"http://lorempixel.com/640/480/people","description":"bandwidth backing up harness","price":"780.00","lng":"-30.3584","lat":"-164.7018","like":53176,"streetAdress":"9304 Kameron Coves","status":true,"star":100,"countryAdress":"French Guiana","stateAdress":"New Jersey"}},"__N_SSG":true}